napari_owncloud/__init__.py
napari_owncloud/_dock_widget.py
napari_owncloud/_tests/__init__.py
napari_owncloud/_tests/test_dock_widget.py
napari_owncloud-0.1.2.dist-info/LICENSE
napari_owncloud-0.1.2.dist-info/METADATA
napari_owncloud-0.1.2.dist-info/WHEEL
napari_owncloud-0.1.2.dist-info/entry_points.txt
napari_owncloud-0.1.2.dist-info/top_level.txt
napari_owncloud-0.1.2.dist-info/RECORD
