Metadata-Version: 2.1
Name: napari-owncloud
Version: 0.1.2
Summary: Browse folders and images in owncloud / nextcloud servers and open them using just a double-click!
Home-page: https://github.com/haesleinhuepf/napari-owncloud
Author: Robert Haase
Author-email: robert.haase@tu-dresden.de
License: BSD-3-Clause
Project-URL: Bug Tracker, https://github.com/haesleinhuepf/napari-owncloud/issues
Project-URL: Documentation, https://github.com/haesleinhuepf/napari-owncloud#README.md
Project-URL: Source Code, https://github.com/haesleinhuepf/napari-owncloud
Project-URL: User Support, https://github.com/haesleinhuepf/napari-owncloud/issues
Classifier: Development Status :: 3 - Alpha
Classifier: Intended Audience :: Science/Research
Classifier: Framework :: napari
Classifier: Topic :: Scientific/Engineering :: Image Processing
Classifier: Programming Language :: Python
Classifier: Programming Language :: Python :: 3
Classifier: Programming Language :: Python :: 3.7
Classifier: Programming Language :: Python :: 3.8
Classifier: Programming Language :: Python :: 3.9
Classifier: Operating System :: OS Independent
Classifier: License :: OSI Approved :: BSD License
Requires-Python: >=3.8
License-File: LICENSE
Requires-Dist: napari-plugin-engine (>=0.1.4)
Requires-Dist: numpy
Requires-Dist: napari-tools-menu
Requires-Dist: pyocclient
